teleSST/__init__.py
teleSST/era5.py
teleSST/ersst5.py
teleSST/seas5.py
teleSST/telesst.py
teleSST/clims/dummy.py
telesst-0.0.3.dist-info/METADATA
telesst-0.0.3.dist-info/WHEEL
telesst-0.0.3.dist-info/licenses/LICENSE
telesst-0.0.3.dist-info/RECORD
