Metadata-Version: 2.4
Name: teleSST
Version: 0.0.3
Summary: Tools for processing Sea Surface Temperature data
Project-URL: Homepage, https://github.com/MutaharChalmers/teleSST
Author-email: Mutahar Chalmers <mutahar.chalmers@gmail.com>
License: MIT License
License-File: LICENSE
Classifier: Development Status :: 4 - Beta
Classifier: Intended Audience :: Science/Research
Classifier: License :: OSI Approved :: MIT License
Classifier: Operating System :: OS Independent
Classifier: Programming Language :: Python :: 3
Classifier: Topic :: Scientific/Engineering
Requires-Python: >=3.8
Requires-Dist: cdsapi>=0.7.4
Requires-Dist: netcdf4>=1.6.4
Requires-Dist: numpy>=1.20.3
Requires-Dist: pandas>=2.0
Requires-Dist: pyarrow>=14.0
Requires-Dist: requests>=2.31
Requires-Dist: scipy>=1.10
Requires-Dist: tqdm>=4.66
Requires-Dist: xarray>=2023.01.0
Requires-Dist: zarr>=2.18
